{
  "en-us": [
    {
      "filename": "README.md",
      "link": "/en-us/docs/admin/README.html",
      "meta": {}
    },
    {
      "filename": "SUMMARY.md",
      "link": "/en-us/docs/admin/SUMMARY.html",
      "meta": {}
    },
    {
      "filename": "admin-console.md",
      "link": "/en-us/docs/admin/install/admin-console.html",
      "meta": {}
    },
    {
      "filename": "consumer-demo.md",
      "link": "/en-us/docs/admin/install/consumer-demo.html",
      "meta": {}
    },
    {
      "filename": "introduction.md",
      "link": "/en-us/docs/admin/install/introduction.html",
      "meta": {}
    },
    {
      "filename": "provider-demo.md",
      "link": "/en-us/docs/admin/install/provider-demo.html",
      "meta": {}
    },
    {
      "filename": "redis.md",
      "link": "/en-us/docs/admin/install/redis.html",
      "meta": {}
    },
    {
      "filename": "simple-monitor-center.md",
      "link": "/en-us/docs/admin/install/simple-monitor-center.html",
      "meta": {}
    },
    {
      "filename": "simple-registry-center.md",
      "link": "/en-us/docs/admin/install/simple-registry-center.html",
      "meta": {}
    },
    {
      "filename": "zookeeper.md",
      "link": "/en-us/docs/admin/install/zookeeper.html",
      "meta": {}
    },
    {
      "filename": "introduction.md",
      "link": "/en-us/docs/admin/introduction.html",
      "meta": {}
    },
    {
      "filename": "dubbo-ops.md",
      "link": "/en-us/docs/admin/ops/dubbo-ops.html",
      "meta": {}
    },
    {
      "filename": "introduction.md",
      "link": "/en-us/docs/admin/ops/introduction.html",
      "meta": {}
    },
    {
      "filename": "pinpoint.md",
      "link": "/en-us/docs/admin/ops/pinpoint.html",
      "meta": {}
    },
    {
      "filename": "skywalking.md",
      "link": "/en-us/docs/admin/ops/skywalking.html",
      "meta": {}
    },
    {
      "filename": "serviceGovernance.md",
      "link": "/en-us/docs/admin/serviceGovernance.html",
      "meta": {}
    },
    {
      "filename": "serviceSearch.md",
      "link": "/en-us/docs/admin/serviceSearch.html",
      "meta": {}
    },
    {
      "filename": "serviceTest.md",
      "link": "/en-us/docs/admin/serviceTest.html",
      "meta": {}
    },
    {
      "filename": "README.md",
      "link": "/en-us/docs/dev/README.html",
      "meta": {}
    },
    {
      "filename": "SPI.md",
      "link": "/en-us/docs/dev/SPI.html",
      "meta": {}
    },
    {
      "filename": "SUMMARY.md",
      "link": "/en-us/docs/dev/SUMMARY.html",
      "meta": {}
    },
    {
      "filename": "TCK.md",
      "link": "/en-us/docs/dev/TCK.html",
      "meta": {}
    },
    {
      "filename": "build.md",
      "link": "/en-us/docs/dev/build.html",
      "meta": {}
    },
    {
      "filename": "checklist.md",
      "link": "/en-us/docs/dev/checklist.html",
      "meta": {}
    },
    {
      "filename": "code-smell.md",
      "link": "/en-us/docs/dev/code-smell.html",
      "meta": {}
    },
    {
      "filename": "coding.md",
      "link": "/en-us/docs/dev/coding.html",
      "meta": {}
    },
    {
      "filename": "contract.md",
      "link": "/en-us/docs/dev/contract.html",
      "meta": {}
    },
    {
      "filename": "contribution.md",
      "link": "/en-us/docs/dev/contribution.html",
      "meta": {}
    },
    {
      "filename": "design.md",
      "link": "/en-us/docs/dev/design.html",
      "meta": {}
    },
    {
      "filename": "implementation.md",
      "link": "/en-us/docs/dev/implementation.html",
      "meta": {}
    },
    {
      "filename": "cache.md",
      "link": "/en-us/docs/dev/impls/cache.html",
      "meta": {}
    },
    {
      "filename": "cluster.md",
      "link": "/en-us/docs/dev/impls/cluster.html",
      "meta": {}
    },
    {
      "filename": "compiler.md",
      "link": "/en-us/docs/dev/impls/compiler.html",
      "meta": {}
    },
    {
      "filename": "container.md",
      "link": "/en-us/docs/dev/impls/container.html",
      "meta": {}
    },
    {
      "filename": "dispatcher.md",
      "link": "/en-us/docs/dev/impls/dispatcher.html",
      "meta": {}
    },
    {
      "filename": "exchanger.md",
      "link": "/en-us/docs/dev/impls/exchanger.html",
      "meta": {}
    },
    {
      "filename": "exporter-listener.md",
      "link": "/en-us/docs/dev/impls/exporter-listener.html",
      "meta": {}
    },
    {
      "filename": "extension-factory.md",
      "link": "/en-us/docs/dev/impls/extension-factory.html",
      "meta": {}
    },
    {
      "filename": "filter.md",
      "link": "/en-us/docs/dev/impls/filter.html",
      "meta": {}
    },
    {
      "filename": "introduction.md",
      "link": "/en-us/docs/dev/impls/introduction.html",
      "meta": {}
    },
    {
      "filename": "invoker-listener.md",
      "link": "/en-us/docs/dev/impls/invoker-listener.html",
      "meta": {}
    },
    {
      "filename": "load-balance.md",
      "link": "/en-us/docs/dev/impls/load-balance.html",
      "meta": {}
    },
    {
      "filename": "logger-adapter.md",
      "link": "/en-us/docs/dev/impls/logger-adapter.html",
      "meta": {}
    },
    {
      "filename": "merger.md",
      "link": "/en-us/docs/dev/impls/merger.html",
      "meta": {}
    },
    {
      "filename": "monitor.md",
      "link": "/en-us/docs/dev/impls/monitor.html",
      "meta": {}
    },
    {
      "filename": "networker.md",
      "link": "/en-us/docs/dev/impls/networker.html",
      "meta": {}
    },
    {
      "filename": "page.md",
      "link": "/en-us/docs/dev/impls/page.html",
      "meta": {}
    },
    {
      "filename": "protocol.md",
      "link": "/en-us/docs/dev/impls/protocol.html",
      "meta": {}
    },
    {
      "filename": "proxy-factory.md",
      "link": "/en-us/docs/dev/impls/proxy-factory.html",
      "meta": {}
    },
    {
      "filename": "registry.md",
      "link": "/en-us/docs/dev/impls/registry.html",
      "meta": {}
    },
    {
      "filename": "remoting.md",
      "link": "/en-us/docs/dev/impls/remoting.html",
      "meta": {}
    },
    {
      "filename": "router.md",
      "link": "/en-us/docs/dev/impls/router.html",
      "meta": {}
    },
    {
      "filename": "serialize.md",
      "link": "/en-us/docs/dev/impls/serialize.html",
      "meta": {}
    },
    {
      "filename": "status-checker.md",
      "link": "/en-us/docs/dev/impls/status-checker.html",
      "meta": {}
    },
    {
      "filename": "telnet-handler.md",
      "link": "/en-us/docs/dev/impls/telnet-handler.html",
      "meta": {}
    },
    {
      "filename": "threadpool.md",
      "link": "/en-us/docs/dev/impls/threadpool.html",
      "meta": {}
    },
    {
      "filename": "validation.md",
      "link": "/en-us/docs/dev/impls/validation.html",
      "meta": {}
    },
    {
      "filename": "introduction.md",
      "link": "/en-us/docs/dev/introduction.html",
      "meta": {}
    },
    {
      "filename": "code-detail.md",
      "link": "/en-us/docs/dev/principals/code-detail.html",
      "meta": {}
    },
    {
      "filename": "configuration.md",
      "link": "/en-us/docs/dev/principals/configuration.html",
      "meta": {}
    },
    {
      "filename": "dummy.md",
      "link": "/en-us/docs/dev/principals/dummy.html",
      "meta": {}
    },
    {
      "filename": "expansibility.md",
      "link": "/en-us/docs/dev/principals/expansibility.html",
      "meta": {}
    },
    {
      "filename": "extension.md",
      "link": "/en-us/docs/dev/principals/extension.html",
      "meta": {}
    },
    {
      "filename": "general-knowledge.md",
      "link": "/en-us/docs/dev/principals/general-knowledge.html",
      "meta": {}
    },
    {
      "filename": "introduction.md",
      "link": "/en-us/docs/dev/principals/introduction.html",
      "meta": {}
    },
    {
      "filename": "robustness.md",
      "link": "/en-us/docs/dev/principals/robustness.html",
      "meta": {}
    },
    {
      "filename": "release.md",
      "link": "/en-us/docs/dev/release.html",
      "meta": {}
    },
    {
      "filename": "apache-dubbo-page_dev.md",
      "link": "/en-us/docs/developers/committer-guide/apache-dubbo-page_dev.html",
      "meta": {}
    },
    {
      "filename": "label-an-issue-guide_dev.md",
      "link": "/en-us/docs/developers/committer-guide/label-an-issue-guide_dev.html",
      "meta": {}
    },
    {
      "filename": "new-committer-guide_dev.md",
      "link": "/en-us/docs/developers/committer-guide/new-committer-guide_dev.html",
      "meta": {}
    },
    {
      "filename": "release-guide_dev.md",
      "link": "/en-us/docs/developers/committer-guide/release-guide_dev.html",
      "meta": {
        "title": "Understanding the Apache Release Cycle",
        "keywords": "Dubbo, Apache, Release"
      }
    },
    {
      "filename": "website-guide_dev.md",
      "link": "/en-us/docs/developers/committer-guide/website-guide_dev.html",
      "meta": {}
    },
    {
      "filename": "become-a-committer_dev.md",
      "link": "/en-us/docs/developers/contributor-guide/become-a-committer_dev.html",
      "meta": {}
    },
    {
      "filename": "cla-signing-guide_dev.md",
      "link": "/en-us/docs/developers/contributor-guide/cla-signing-guide_dev.html",
      "meta": {}
    },
    {
      "filename": "dubbo-extension-guide_dev.md",
      "link": "/en-us/docs/developers/contributor-guide/dubbo-extension-guide_dev.html",
      "meta": {}
    },
    {
      "filename": "mailing-list-subscription-guide_dev.md",
      "link": "/en-us/docs/developers/contributor-guide/mailing-list-subscription-guide_dev.html",
      "meta": {}
    },
    {
      "filename": "new-contributor-guide_dev.md",
      "link": "/en-us/docs/developers/contributor-guide/new-contributor-guide_dev.html",
      "meta": {}
    },
    {
      "filename": "reporting-security-issues_dev.md",
      "link": "/en-us/docs/developers/contributor-guide/reporting-security-issues_dev.html",
      "meta": {}
    },
    {
      "filename": "software-donation-guide_dev.md",
      "link": "/en-us/docs/developers/contributor-guide/software-donation-guide_dev.html",
      "meta": {}
    },
    {
      "filename": "test-coverage-guide_dev.md",
      "link": "/en-us/docs/developers/contributor-guide/test-coverage-guide_dev.html",
      "meta": {}
    },
    {
      "filename": "developers_dev.md",
      "link": "/en-us/docs/developers/developers_dev.html",
      "meta": {}
    },
    {
      "filename": "guide_dev.md",
      "link": "/en-us/docs/developers/guide_dev.html",
      "meta": {}
    },
    {
      "filename": "faq_dev.md",
      "link": "/en-us/docs/developers/user-guide/faq_dev.html",
      "meta": {}
    },
    {
      "filename": "README.md",
      "link": "/en-us/docs/user/README.html",
      "meta": {}
    },
    {
      "filename": "SUMMARY.md",
      "link": "/en-us/docs/user/SUMMARY.html",
      "meta": {}
    },
    {
      "filename": "benchmark-tool.md",
      "link": "/en-us/docs/user/benchmark-tool.html",
      "meta": {}
    },
    {
      "filename": "best-practice.md",
      "link": "/en-us/docs/user/best-practice.html",
      "meta": {}
    },
    {
      "filename": "capacity-plan.md",
      "link": "/en-us/docs/user/capacity-plan.html",
      "meta": {}
    },
    {
      "filename": "annotation.md",
      "link": "/en-us/docs/user/configuration/annotation.html",
      "meta": {}
    },
    {
      "filename": "api.md",
      "link": "/en-us/docs/user/configuration/api.html",
      "meta": {}
    },
    {
      "filename": "index.md",
      "link": "/en-us/docs/user/configuration/index.html",
      "meta": {}
    },
    {
      "filename": "properties.md",
      "link": "/en-us/docs/user/configuration/properties.html",
      "meta": {}
    },
    {
      "filename": "xml.md",
      "link": "/en-us/docs/user/configuration/xml.html",
      "meta": {}
    },
    {
      "filename": "coveragence.md",
      "link": "/en-us/docs/user/coveragence.html",
      "meta": {}
    },
    {
      "filename": "accesslog.md",
      "link": "/en-us/docs/user/demos/accesslog.html",
      "meta": {}
    },
    {
      "filename": "async-call.md",
      "link": "/en-us/docs/user/demos/async-call.html",
      "meta": {}
    },
    {
      "filename": "attachment.md",
      "link": "/en-us/docs/user/demos/attachment.html",
      "meta": {}
    },
    {
      "filename": "callback-parameter.md",
      "link": "/en-us/docs/user/demos/callback-parameter.html",
      "meta": {}
    },
    {
      "filename": "concurrency-control.md",
      "link": "/en-us/docs/user/demos/concurrency-control.html",
      "meta": {}
    },
    {
      "filename": "config-connections.md",
      "link": "/en-us/docs/user/demos/config-connections.html",
      "meta": {}
    },
    {
      "filename": "config-rule.md",
      "link": "/en-us/docs/user/demos/config-rule.html",
      "meta": {}
    },
    {
      "filename": "context.md",
      "link": "/en-us/docs/user/demos/context.html",
      "meta": {}
    },
    {
      "filename": "delay-publish.md",
      "link": "/en-us/docs/user/demos/delay-publish.html",
      "meta": {}
    },
    {
      "filename": "distributed-transaction.md",
      "link": "/en-us/docs/user/demos/distributed-transaction.html",
      "meta": {}
    },
    {
      "filename": "dump.md",
      "link": "/en-us/docs/user/demos/dump.html",
      "meta": {}
    },
    {
      "filename": "echo-service.md",
      "link": "/en-us/docs/user/demos/echo-service.html",
      "meta": {}
    },
    {
      "filename": "events-notify.md",
      "link": "/en-us/docs/user/demos/events-notify.html",
      "meta": {}
    },
    {
      "filename": "explicit-target.md",
      "link": "/en-us/docs/user/demos/explicit-target.html",
      "meta": {}
    },
    {
      "filename": "fault-tolerent-strategy.md",
      "link": "/en-us/docs/user/demos/fault-tolerent-strategy.html",
      "meta": {}
    },
    {
      "filename": "generic-reference.md",
      "link": "/en-us/docs/user/demos/generic-reference.html",
      "meta": {}
    },
    {
      "filename": "generic-service.md",
      "link": "/en-us/docs/user/demos/generic-service.html",
      "meta": {}
    },
    {
      "filename": "graceful-shutdown.md",
      "link": "/en-us/docs/user/demos/graceful-shutdown.html",
      "meta": {}
    },
    {
      "filename": "group-merger.md",
      "link": "/en-us/docs/user/demos/group-merger.html",
      "meta": {}
    },
    {
      "filename": "hostname-binding.md",
      "link": "/en-us/docs/user/demos/hostname-binding.html",
      "meta": {}
    },
    {
      "filename": "index.md",
      "link": "/en-us/docs/user/demos/index.html",
      "meta": {}
    },
    {
      "filename": "introduction.md",
      "link": "/en-us/docs/user/demos/introduction.html",
      "meta": {}
    },
    {
      "filename": "lazy-connect.md",
      "link": "/en-us/docs/user/demos/lazy-connect.html",
      "meta": {}
    },
    {
      "filename": "loadbalance.md",
      "link": "/en-us/docs/user/demos/loadbalance.html",
      "meta": {}
    },
    {
      "filename": "local-call.md",
      "link": "/en-us/docs/user/demos/local-call.html",
      "meta": {}
    },
    {
      "filename": "local-mock.md",
      "link": "/en-us/docs/user/demos/local-mock.html",
      "meta": {}
    },
    {
      "filename": "local-stub.md",
      "link": "/en-us/docs/user/demos/local-stub.html",
      "meta": {}
    },
    {
      "filename": "logger-strategy.md",
      "link": "/en-us/docs/user/demos/logger-strategy.html",
      "meta": {}
    },
    {
      "filename": "multi-protocols.md",
      "link": "/en-us/docs/user/demos/multi-protocols.html",
      "meta": {}
    },
    {
      "filename": "multi-registry.md",
      "link": "/en-us/docs/user/demos/multi-registry.html",
      "meta": {}
    },
    {
      "filename": "multi-versions.md",
      "link": "/en-us/docs/user/demos/multi-versions.html",
      "meta": {}
    },
    {
      "filename": "netty4.md",
      "link": "/en-us/docs/user/demos/netty4.html",
      "meta": {}
    },
    {
      "filename": "parameter-validation.md",
      "link": "/en-us/docs/user/demos/parameter-validation.html",
      "meta": {}
    },
    {
      "filename": "preflight-check.md",
      "link": "/en-us/docs/user/demos/preflight-check.html",
      "meta": {}
    },
    {
      "filename": "reference-config-cache.md",
      "link": "/en-us/docs/user/demos/reference-config-cache.html",
      "meta": {}
    },
    {
      "filename": "registry-only.md",
      "link": "/en-us/docs/user/demos/registry-only.html",
      "meta": {}
    },
    {
      "filename": "result-cache.md",
      "link": "/en-us/docs/user/demos/result-cache.html",
      "meta": {}
    },
    {
      "filename": "routing-rule.md",
      "link": "/en-us/docs/user/demos/routing-rule.html",
      "meta": {}
    },
    {
      "filename": "serialization.md",
      "link": "/en-us/docs/user/demos/serialization.html",
      "meta": {}
    },
    {
      "filename": "service-container.md",
      "link": "/en-us/docs/user/demos/service-container.html",
      "meta": {}
    },
    {
      "filename": "service-downgrade.md",
      "link": "/en-us/docs/user/demos/service-downgrade.html",
      "meta": {}
    },
    {
      "filename": "service-group.md",
      "link": "/en-us/docs/user/demos/service-group.html",
      "meta": {}
    },
    {
      "filename": "static-service.md",
      "link": "/en-us/docs/user/demos/static-service.html",
      "meta": {}
    },
    {
      "filename": "stickiness.md",
      "link": "/en-us/docs/user/demos/stickiness.html",
      "meta": {}
    },
    {
      "filename": "subscribe-only.md",
      "link": "/en-us/docs/user/demos/subscribe-only.html",
      "meta": {}
    },
    {
      "filename": "thread-model.md",
      "link": "/en-us/docs/user/demos/thread-model.html",
      "meta": {}
    },
    {
      "filename": "token-authorization.md",
      "link": "/en-us/docs/user/demos/token-authorization.html",
      "meta": {}
    },
    {
      "filename": "dependencies.md",
      "link": "/en-us/docs/user/dependencies.html",
      "meta": {}
    },
    {
      "filename": "reference.md",
      "link": "/en-us/docs/user/languages/erlang/reference.html",
      "meta": {}
    },
    {
      "filename": "serialization.md",
      "link": "/en-us/docs/user/languages/erlang/serialization.html",
      "meta": {}
    },
    {
      "filename": "service.md",
      "link": "/en-us/docs/user/languages/erlang/service.html",
      "meta": {}
    },
    {
      "filename": "start.md",
      "link": "/en-us/docs/user/languages/erlang/start.html",
      "meta": {}
    },
    {
      "filename": "maturity.md",
      "link": "/en-us/docs/user/maturity.html",
      "meta": {}
    },
    {
      "filename": "perf-test.md",
      "link": "/en-us/docs/user/perf-test.html",
      "meta": {}
    },
    {
      "filename": "architecture.md",
      "link": "/en-us/docs/user/preface/architecture.html",
      "meta": {}
    },
    {
      "filename": "background.md",
      "link": "/en-us/docs/user/preface/background.html",
      "meta": {}
    },
    {
      "filename": "index.md",
      "link": "/en-us/docs/user/preface/index.html",
      "meta": {}
    },
    {
      "filename": "requirements.md",
      "link": "/en-us/docs/user/preface/requirements.html",
      "meta": {}
    },
    {
      "filename": "usage.md",
      "link": "/en-us/docs/user/preface/usage.html",
      "meta": {}
    },
    {
      "filename": "quick-start.md",
      "link": "/en-us/docs/user/quick-start.html",
      "meta": {}
    },
    {
      "filename": "recommend.md",
      "link": "/en-us/docs/user/recommend.html",
      "meta": {}
    },
    {
      "filename": "api.md",
      "link": "/en-us/docs/user/references/api.html",
      "meta": {}
    },
    {
      "filename": "maven.md",
      "link": "/en-us/docs/user/references/maven.html",
      "meta": {}
    },
    {
      "filename": "dubbo.md",
      "link": "/en-us/docs/user/references/protocol/dubbo.html",
      "meta": {}
    },
    {
      "filename": "hessian.md",
      "link": "/en-us/docs/user/references/protocol/hessian.html",
      "meta": {}
    },
    {
      "filename": "http.md",
      "link": "/en-us/docs/user/references/protocol/http.html",
      "meta": {}
    },
    {
      "filename": "introduction.md",
      "link": "/en-us/docs/user/references/protocol/introduction.html",
      "meta": {}
    },
    {
      "filename": "memcached.md",
      "link": "/en-us/docs/user/references/protocol/memcached.html",
      "meta": {}
    },
    {
      "filename": "redis.md",
      "link": "/en-us/docs/user/references/protocol/redis.html",
      "meta": {}
    },
    {
      "filename": "rest.md",
      "link": "/en-us/docs/user/references/protocol/rest.html",
      "meta": {}
    },
    {
      "filename": "rmi.md",
      "link": "/en-us/docs/user/references/protocol/rmi.html",
      "meta": {}
    },
    {
      "filename": "thrift.md",
      "link": "/en-us/docs/user/references/protocol/thrift.html",
      "meta": {}
    },
    {
      "filename": "webservice.md",
      "link": "/en-us/docs/user/references/protocol/webservice.html",
      "meta": {}
    },
    {
      "filename": "qos.md",
      "link": "/en-us/docs/user/references/qos.html",
      "meta": {}
    },
    {
      "filename": "introduction.md",
      "link": "/en-us/docs/user/references/registry/introduction.html",
      "meta": {}
    },
    {
      "filename": "multicast.md",
      "link": "/en-us/docs/user/references/registry/multicast.html",
      "meta": {}
    },
    {
      "filename": "nacos.md",
      "link": "/en-us/docs/user/references/registry/nacos.html",
      "meta": {}
    },
    {
      "filename": "redis.md",
      "link": "/en-us/docs/user/references/registry/redis.html",
      "meta": {}
    },
    {
      "filename": "simple.md",
      "link": "/en-us/docs/user/references/registry/simple.html",
      "meta": {}
    },
    {
      "filename": "zookeeper.md",
      "link": "/en-us/docs/user/references/registry/zookeeper.html",
      "meta": {}
    },
    {
      "filename": "telnet.md",
      "link": "/en-us/docs/user/references/telnet.html",
      "meta": {}
    },
    {
      "filename": "dubbo-application.md",
      "link": "/en-us/docs/user/references/xml/dubbo-application.html",
      "meta": {}
    },
    {
      "filename": "dubbo-argument.md",
      "link": "/en-us/docs/user/references/xml/dubbo-argument.html",
      "meta": {}
    },
    {
      "filename": "dubbo-consumer.md",
      "link": "/en-us/docs/user/references/xml/dubbo-consumer.html",
      "meta": {}
    },
    {
      "filename": "dubbo-method.md",
      "link": "/en-us/docs/user/references/xml/dubbo-method.html",
      "meta": {}
    },
    {
      "filename": "dubbo-module.md",
      "link": "/en-us/docs/user/references/xml/dubbo-module.html",
      "meta": {}
    },
    {
      "filename": "dubbo-monitor.md",
      "link": "/en-us/docs/user/references/xml/dubbo-monitor.html",
      "meta": {}
    },
    {
      "filename": "dubbo-parameter.md",
      "link": "/en-us/docs/user/references/xml/dubbo-parameter.html",
      "meta": {}
    },
    {
      "filename": "dubbo-protocol.md",
      "link": "/en-us/docs/user/references/xml/dubbo-protocol.html",
      "meta": {}
    },
    {
      "filename": "dubbo-provider.md",
      "link": "/en-us/docs/user/references/xml/dubbo-provider.html",
      "meta": {}
    },
    {
      "filename": "dubbo-reference.md",
      "link": "/en-us/docs/user/references/xml/dubbo-reference.html",
      "meta": {}
    },
    {
      "filename": "dubbo-registry.md",
      "link": "/en-us/docs/user/references/xml/dubbo-registry.html",
      "meta": {}
    },
    {
      "filename": "dubbo-service.md",
      "link": "/en-us/docs/user/references/xml/dubbo-service.html",
      "meta": {}
    },
    {
      "filename": "introduction.md",
      "link": "/en-us/docs/user/references/xml/introduction.html",
      "meta": {}
    },
    {
      "filename": "rest.md",
      "link": "/en-us/docs/user/rest.html",
      "meta": {}
    },
    {
      "filename": "simple-monitor.md",
      "link": "/en-us/docs/user/simple-monitor.html",
      "meta": {}
    }
  ],
  "zh-cn": [
    {
      "filename": "README.md",
      "link": "/zh-cn/docs/admin/README.html",
      "meta": {}
    },
    {
      "filename": "SUMMARY.md",
      "link": "/zh-cn/docs/admin/SUMMARY.html",
      "meta": {}
    },
    {
      "filename": "admin-console.md",
      "link": "/zh-cn/docs/admin/install/admin-console.html",
      "meta": {}
    },
    {
      "filename": "consumer-demo.md",
      "link": "/zh-cn/docs/admin/install/consumer-demo.html",
      "meta": {}
    },
    {
      "filename": "introduction.md",
      "link": "/zh-cn/docs/admin/install/introduction.html",
      "meta": {}
    },
    {
      "filename": "provider-demo.md",
      "link": "/zh-cn/docs/admin/install/provider-demo.html",
      "meta": {}
    },
    {
      "filename": "redis.md",
      "link": "/zh-cn/docs/admin/install/redis.html",
      "meta": {}
    },
    {
      "filename": "simple-monitor-center.md",
      "link": "/zh-cn/docs/admin/install/simple-monitor-center.html",
      "meta": {}
    },
    {
      "filename": "simple-registry-center.md",
      "link": "/zh-cn/docs/admin/install/simple-registry-center.html",
      "meta": {}
    },
    {
      "filename": "zookeeper.md",
      "link": "/zh-cn/docs/admin/install/zookeeper.html",
      "meta": {}
    },
    {
      "filename": "introduction.md",
      "link": "/zh-cn/docs/admin/introduction.html",
      "meta": {}
    },
    {
      "filename": "dubbo-ops.md",
      "link": "/zh-cn/docs/admin/ops/dubbo-ops.html",
      "meta": {}
    },
    {
      "filename": "introduction.md",
      "link": "/zh-cn/docs/admin/ops/introduction.html",
      "meta": {}
    },
    {
      "filename": "pinpoint.md",
      "link": "/zh-cn/docs/admin/ops/pinpoint.html",
      "meta": {}
    },
    {
      "filename": "skywalking.md",
      "link": "/zh-cn/docs/admin/ops/skywalking.html",
      "meta": {}
    },
    {
      "filename": "serviceGovernance.md",
      "link": "/zh-cn/docs/admin/serviceGovernance.html",
      "meta": {}
    },
    {
      "filename": "serviceSearch.md",
      "link": "/zh-cn/docs/admin/serviceSearch.html",
      "meta": {}
    },
    {
      "filename": "serviceTest.md",
      "link": "/zh-cn/docs/admin/serviceTest.html",
      "meta": {}
    },
    {
      "filename": "README.md",
      "link": "/zh-cn/docs/dev/README.html",
      "meta": {}
    },
    {
      "filename": "SPI.md",
      "link": "/zh-cn/docs/dev/SPI.html",
      "meta": {}
    },
    {
      "filename": "SUMMARY.md",
      "link": "/zh-cn/docs/dev/SUMMARY.html",
      "meta": {}
    },
    {
      "filename": "TCK.md",
      "link": "/zh-cn/docs/dev/TCK.html",
      "meta": {}
    },
    {
      "filename": "build.md",
      "link": "/zh-cn/docs/dev/build.html",
      "meta": {}
    },
    {
      "filename": "checklist.md",
      "link": "/zh-cn/docs/dev/checklist.html",
      "meta": {}
    },
    {
      "filename": "code-smell.md",
      "link": "/zh-cn/docs/dev/code-smell.html",
      "meta": {}
    },
    {
      "filename": "coding.md",
      "link": "/zh-cn/docs/dev/coding.html",
      "meta": {}
    },
    {
      "filename": "contract.md",
      "link": "/zh-cn/docs/dev/contract.html",
      "meta": {}
    },
    {
      "filename": "contribution.md",
      "link": "/zh-cn/docs/dev/contribution.html",
      "meta": {}
    },
    {
      "filename": "design.md",
      "link": "/zh-cn/docs/dev/design.html",
      "meta": {}
    },
    {
      "filename": "implementation.md",
      "link": "/zh-cn/docs/dev/implementation.html",
      "meta": {}
    },
    {
      "filename": "cache.md",
      "link": "/zh-cn/docs/dev/impls/cache.html",
      "meta": {}
    },
    {
      "filename": "cluster.md",
      "link": "/zh-cn/docs/dev/impls/cluster.html",
      "meta": {}
    },
    {
      "filename": "compiler.md",
      "link": "/zh-cn/docs/dev/impls/compiler.html",
      "meta": {}
    },
    {
      "filename": "container.md",
      "link": "/zh-cn/docs/dev/impls/container.html",
      "meta": {}
    },
    {
      "filename": "dispatcher.md",
      "link": "/zh-cn/docs/dev/impls/dispatcher.html",
      "meta": {}
    },
    {
      "filename": "exchanger.md",
      "link": "/zh-cn/docs/dev/impls/exchanger.html",
      "meta": {}
    },
    {
      "filename": "exporter-listener.md",
      "link": "/zh-cn/docs/dev/impls/exporter-listener.html",
      "meta": {}
    },
    {
      "filename": "extension-factory.md",
      "link": "/zh-cn/docs/dev/impls/extension-factory.html",
      "meta": {}
    },
    {
      "filename": "filter.md",
      "link": "/zh-cn/docs/dev/impls/filter.html",
      "meta": {}
    },
    {
      "filename": "introduction.md",
      "link": "/zh-cn/docs/dev/impls/introduction.html",
      "meta": {}
    },
    {
      "filename": "invoker-listener.md",
      "link": "/zh-cn/docs/dev/impls/invoker-listener.html",
      "meta": {}
    },
    {
      "filename": "load-balance.md",
      "link": "/zh-cn/docs/dev/impls/load-balance.html",
      "meta": {}
    },
    {
      "filename": "logger-adapter.md",
      "link": "/zh-cn/docs/dev/impls/logger-adapter.html",
      "meta": {}
    },
    {
      "filename": "merger.md",
      "link": "/zh-cn/docs/dev/impls/merger.html",
      "meta": {}
    },
    {
      "filename": "monitor.md",
      "link": "/zh-cn/docs/dev/impls/monitor.html",
      "meta": {}
    },
    {
      "filename": "networker.md",
      "link": "/zh-cn/docs/dev/impls/networker.html",
      "meta": {}
    },
    {
      "filename": "page.md",
      "link": "/zh-cn/docs/dev/impls/page.html",
      "meta": {}
    },
    {
      "filename": "protocol.md",
      "link": "/zh-cn/docs/dev/impls/protocol.html",
      "meta": {}
    },
    {
      "filename": "proxy-factory.md",
      "link": "/zh-cn/docs/dev/impls/proxy-factory.html",
      "meta": {}
    },
    {
      "filename": "registry.md",
      "link": "/zh-cn/docs/dev/impls/registry.html",
      "meta": {}
    },
    {
      "filename": "remoting.md",
      "link": "/zh-cn/docs/dev/impls/remoting.html",
      "meta": {}
    },
    {
      "filename": "router.md",
      "link": "/zh-cn/docs/dev/impls/router.html",
      "meta": {}
    },
    {
      "filename": "serialize.md",
      "link": "/zh-cn/docs/dev/impls/serialize.html",
      "meta": {}
    },
    {
      "filename": "status-checker.md",
      "link": "/zh-cn/docs/dev/impls/status-checker.html",
      "meta": {}
    },
    {
      "filename": "telnet-handler.md",
      "link": "/zh-cn/docs/dev/impls/telnet-handler.html",
      "meta": {}
    },
    {
      "filename": "threadpool.md",
      "link": "/zh-cn/docs/dev/impls/threadpool.html",
      "meta": {}
    },
    {
      "filename": "validation.md",
      "link": "/zh-cn/docs/dev/impls/validation.html",
      "meta": {}
    },
    {
      "filename": "introduction.md",
      "link": "/zh-cn/docs/dev/introduction.html",
      "meta": {}
    },
    {
      "filename": "code-detail.md",
      "link": "/zh-cn/docs/dev/principals/code-detail.html",
      "meta": {}
    },
    {
      "filename": "configuration.md",
      "link": "/zh-cn/docs/dev/principals/configuration.html",
      "meta": {}
    },
    {
      "filename": "dummy.md",
      "link": "/zh-cn/docs/dev/principals/dummy.html",
      "meta": {}
    },
    {
      "filename": "expansibility.md",
      "link": "/zh-cn/docs/dev/principals/expansibility.html",
      "meta": {}
    },
    {
      "filename": "extension.md",
      "link": "/zh-cn/docs/dev/principals/extension.html",
      "meta": {}
    },
    {
      "filename": "general-knowledge.md",
      "link": "/zh-cn/docs/dev/principals/general-knowledge.html",
      "meta": {}
    },
    {
      "filename": "introduction.md",
      "link": "/zh-cn/docs/dev/principals/introduction.html",
      "meta": {}
    },
    {
      "filename": "robustness.md",
      "link": "/zh-cn/docs/dev/principals/robustness.html",
      "meta": {}
    },
    {
      "filename": "release.md",
      "link": "/zh-cn/docs/dev/release.html",
      "meta": {}
    },
    {
      "filename": "apache-dubbo-page_dev.md",
      "link": "/zh-cn/docs/developers/committer-guide/apache-dubbo-page_dev.html",
      "meta": {}
    },
    {
      "filename": "label-an-issue-guide_dev.md",
      "link": "/zh-cn/docs/developers/committer-guide/label-an-issue-guide_dev.html",
      "meta": {}
    },
    {
      "filename": "new-committer-guide_dev.md",
      "link": "/zh-cn/docs/developers/committer-guide/new-committer-guide_dev.html",
      "meta": {}
    },
    {
      "filename": "release-guide_dev.md",
      "link": "/zh-cn/docs/developers/committer-guide/release-guide_dev.html",
      "meta": {
        "title": "如何准备Apache Release",
        "keywords": "Dubbo, Apache, Release"
      }
    },
    {
      "filename": "website-guide_dev.md",
      "link": "/zh-cn/docs/developers/committer-guide/website-guide_dev.html",
      "meta": {}
    },
    {
      "filename": "become-a-committer_dev.md",
      "link": "/zh-cn/docs/developers/contributor-guide/become-a-committer_dev.html",
      "meta": {}
    },
    {
      "filename": "cla-signing-guide_dev.md",
      "link": "/zh-cn/docs/developers/contributor-guide/cla-signing-guide_dev.html",
      "meta": {}
    },
    {
      "filename": "dubbo-extension-guide_dev.md",
      "link": "/zh-cn/docs/developers/contributor-guide/dubbo-extension-guide_dev.html",
      "meta": {}
    },
    {
      "filename": "mailing-list-subscription-guide_dev.md",
      "link": "/zh-cn/docs/developers/contributor-guide/mailing-list-subscription-guide_dev.html",
      "meta": {}
    },
    {
      "filename": "new-contributor-guide_dev.md",
      "link": "/zh-cn/docs/developers/contributor-guide/new-contributor-guide_dev.html",
      "meta": {}
    },
    {
      "filename": "reporting-security-issues_dev.md",
      "link": "/zh-cn/docs/developers/contributor-guide/reporting-security-issues_dev.html",
      "meta": {}
    },
    {
      "filename": "software-donation-guide_dev.md",
      "link": "/zh-cn/docs/developers/contributor-guide/software-donation-guide_dev.html",
      "meta": {}
    },
    {
      "filename": "test-coverage-guide_dev.md",
      "link": "/zh-cn/docs/developers/contributor-guide/test-coverage-guide_dev.html",
      "meta": {}
    },
    {
      "filename": "developers_dev.md",
      "link": "/zh-cn/docs/developers/developers_dev.html",
      "meta": {}
    },
    {
      "filename": "guide_dev.md",
      "link": "/zh-cn/docs/developers/guide_dev.html",
      "meta": {}
    },
    {
      "filename": "faq_dev.md",
      "link": "/zh-cn/docs/developers/user-guide/faq_dev.html",
      "meta": {}
    },
    {
      "filename": "adaptive-extension.md",
      "link": "/zh-cn/docs/source_code_guide/adaptive-extension.html",
      "meta": {
        "title": "SPI 自适应拓展",
        "keywords": "Dubbo, SPI, Adaptive Extension",
        "description": "本文介绍了自适应拓展的原理和实现细节"
      }
    },
    {
      "filename": "cluster.md",
      "link": "/zh-cn/docs/source_code_guide/cluster.html",
      "meta": {
        "title": "集群",
        "keywords": "Dubbo, Cluster",
        "description": "本文介绍了集群的原理和实现细节"
      }
    },
    {
      "filename": "directory.md",
      "link": "/zh-cn/docs/source_code_guide/directory.html",
      "meta": {
        "title": "服务目录",
        "keywords": "Dubbo, Directory",
        "description": "本文介绍了服务目录的原理和实现细节"
      }
    },
    {
      "filename": "dubbo-spi.md",
      "link": "/zh-cn/docs/source_code_guide/dubbo-spi.html",
      "meta": {
        "title": "Dubbo SPI",
        "keywords": "Dubbo, SPI",
        "description": "本文介绍了 Dubbo SPI 的原理和实现细节"
      }
    },
    {
      "filename": "export-service.md",
      "link": "/zh-cn/docs/source_code_guide/export-service.html",
      "meta": {
        "title": "服务导出",
        "keywords": "Dubbo, service, export",
        "description": "本文介绍了 Dubbo 服务导出的过程和实现细节"
      }
    },
    {
      "filename": "loadbalance.md",
      "link": "/zh-cn/docs/source_code_guide/loadbalance.html",
      "meta": {
        "title": "负载均衡",
        "keywords": "Dubbo, LoadBalance",
        "description": "本文介绍了集群的原理和实现细节"
      }
    },
    {
      "filename": "refer-service.md",
      "link": "/zh-cn/docs/source_code_guide/refer-service.html",
      "meta": {
        "title": "服务引用",
        "keywords": "Dubbo, service, refer",
        "description": "本文介绍了 Dubbo 服务引用的过程和实现细节"
      }
    },
    {
      "filename": "router.md",
      "link": "/zh-cn/docs/source_code_guide/router.html",
      "meta": {
        "title": "服务路由",
        "keywords": "Dubbo, Router",
        "description": "本文介绍了服务\b路由的原理和实现细节"
      }
    },
    {
      "filename": "service-invoking-process.md",
      "link": "/zh-cn/docs/source_code_guide/service-invoking-process.html",
      "meta": {
        "title": "服务调用过程",
        "keywords": "Dubbo, Service",
        "description": "本文介绍了服务调用过程\b的原理和实现细节"
      }
    },
    {
      "filename": "README.md",
      "link": "/zh-cn/docs/user/README.html",
      "meta": {}
    },
    {
      "filename": "SUMMARY.md",
      "link": "/zh-cn/docs/user/SUMMARY.html",
      "meta": {}
    },
    {
      "filename": "benchmark-tool.md",
      "link": "/zh-cn/docs/user/benchmark-tool.html",
      "meta": {}
    },
    {
      "filename": "best-practice.md",
      "link": "/zh-cn/docs/user/best-practice.html",
      "meta": {
        "title": "服务化最佳实践",
        "keywords": "分包, 粒度, 版本, 兼容性, 枚举, 序列化，异常",
        "description": "Dubbo 最佳实践"
      }
    },
    {
      "filename": "capacity-plan.md",
      "link": "/zh-cn/docs/user/capacity-plan.html",
      "meta": {
        "title": "容量规划",
        "keywords": "容量规划",
        "description": "Dubbo 应用容量规划参考"
      }
    },
    {
      "filename": "annotation.md",
      "link": "/zh-cn/docs/user/configuration/annotation.html",
      "meta": {}
    },
    {
      "filename": "api.md",
      "link": "/zh-cn/docs/user/configuration/api.html",
      "meta": {}
    },
    {
      "filename": "config-center.md",
      "link": "/zh-cn/docs/user/configuration/config-center.html",
      "meta": {}
    },
    {
      "filename": "configuration-load-process.md",
      "link": "/zh-cn/docs/user/configuration/configuration-load-process.html",
      "meta": {}
    },
    {
      "filename": "index.md",
      "link": "/zh-cn/docs/user/configuration/index.html",
      "meta": {}
    },
    {
      "filename": "properties-deprecated.md",
      "link": "/zh-cn/docs/user/configuration/properties-deprecated.html",
      "meta": {}
    },
    {
      "filename": "xml.md",
      "link": "/zh-cn/docs/user/configuration/xml.html",
      "meta": {}
    },
    {
      "filename": "coveragence.md",
      "link": "/zh-cn/docs/user/coveragence.html",
      "meta": {}
    },
    {
      "filename": "accesslog.md",
      "link": "/zh-cn/docs/user/demos/accesslog.html",
      "meta": {}
    },
    {
      "filename": "async-call-deprecated.md",
      "link": "/zh-cn/docs/user/demos/async-call-deprecated.html",
      "meta": {}
    },
    {
      "filename": "async-call.md",
      "link": "/zh-cn/docs/user/demos/async-call.html",
      "meta": {}
    },
    {
      "filename": "async-execute-on-provider.md",
      "link": "/zh-cn/docs/user/demos/async-execute-on-provider.html",
      "meta": {}
    },
    {
      "filename": "attachment.md",
      "link": "/zh-cn/docs/user/demos/attachment.html",
      "meta": {}
    },
    {
      "filename": "callback-parameter.md",
      "link": "/zh-cn/docs/user/demos/callback-parameter.html",
      "meta": {}
    },
    {
      "filename": "concurrency-control.md",
      "link": "/zh-cn/docs/user/demos/concurrency-control.html",
      "meta": {}
    },
    {
      "filename": "config-connections.md",
      "link": "/zh-cn/docs/user/demos/config-connections.html",
      "meta": {}
    },
    {
      "filename": "config-rule-deprecated.md",
      "link": "/zh-cn/docs/user/demos/config-rule-deprecated.html",
      "meta": {}
    },
    {
      "filename": "config-rule.md",
      "link": "/zh-cn/docs/user/demos/config-rule.html",
      "meta": {}
    },
    {
      "filename": "context.md",
      "link": "/zh-cn/docs/user/demos/context.html",
      "meta": {}
    },
    {
      "filename": "delay-publish.md",
      "link": "/zh-cn/docs/user/demos/delay-publish.html",
      "meta": {}
    },
    {
      "filename": "distributed-transaction.md",
      "link": "/zh-cn/docs/user/demos/distributed-transaction.html",
      "meta": {}
    },
    {
      "filename": "dump.md",
      "link": "/zh-cn/docs/user/demos/dump.html",
      "meta": {}
    },
    {
      "filename": "echo-service.md",
      "link": "/zh-cn/docs/user/demos/echo-service.html",
      "meta": {}
    },
    {
      "filename": "events-notify.md",
      "link": "/zh-cn/docs/user/demos/events-notify.html",
      "meta": {}
    },
    {
      "filename": "explicit-target.md",
      "link": "/zh-cn/docs/user/demos/explicit-target.html",
      "meta": {}
    },
    {
      "filename": "fault-tolerent-strategy.md",
      "link": "/zh-cn/docs/user/demos/fault-tolerent-strategy.html",
      "meta": {}
    },
    {
      "filename": "generic-reference.md",
      "link": "/zh-cn/docs/user/demos/generic-reference.html",
      "meta": {}
    },
    {
      "filename": "generic-service.md",
      "link": "/zh-cn/docs/user/demos/generic-service.html",
      "meta": {}
    },
    {
      "filename": "graceful-shutdown.md",
      "link": "/zh-cn/docs/user/demos/graceful-shutdown.html",
      "meta": {}
    },
    {
      "filename": "group-merger.md",
      "link": "/zh-cn/docs/user/demos/group-merger.html",
      "meta": {}
    },
    {
      "filename": "hostname-binding.md",
      "link": "/zh-cn/docs/user/demos/hostname-binding.html",
      "meta": {}
    },
    {
      "filename": "index.md",
      "link": "/zh-cn/docs/user/demos/index.html",
      "meta": {}
    },
    {
      "filename": "introduction.md",
      "link": "/zh-cn/docs/user/demos/introduction.html",
      "meta": {}
    },
    {
      "filename": "lazy-connect.md",
      "link": "/zh-cn/docs/user/demos/lazy-connect.html",
      "meta": {}
    },
    {
      "filename": "loadbalance.md",
      "link": "/zh-cn/docs/user/demos/loadbalance.html",
      "meta": {}
    },
    {
      "filename": "local-call.md",
      "link": "/zh-cn/docs/user/demos/local-call.html",
      "meta": {}
    },
    {
      "filename": "local-mock.md",
      "link": "/zh-cn/docs/user/demos/local-mock.html",
      "meta": {}
    },
    {
      "filename": "local-stub.md",
      "link": "/zh-cn/docs/user/demos/local-stub.html",
      "meta": {}
    },
    {
      "filename": "logger-strategy.md",
      "link": "/zh-cn/docs/user/demos/logger-strategy.html",
      "meta": {}
    },
    {
      "filename": "multi-protocols.md",
      "link": "/zh-cn/docs/user/demos/multi-protocols.html",
      "meta": {}
    },
    {
      "filename": "multi-registry.md",
      "link": "/zh-cn/docs/user/demos/multi-registry.html",
      "meta": {}
    },
    {
      "filename": "multi-versions.md",
      "link": "/zh-cn/docs/user/demos/multi-versions.html",
      "meta": {}
    },
    {
      "filename": "netty4.md",
      "link": "/zh-cn/docs/user/demos/netty4.html",
      "meta": {}
    },
    {
      "filename": "parameter-validation.md",
      "link": "/zh-cn/docs/user/demos/parameter-validation.html",
      "meta": {}
    },
    {
      "filename": "preflight-check.md",
      "link": "/zh-cn/docs/user/demos/preflight-check.html",
      "meta": {}
    },
    {
      "filename": "reference-config-cache.md",
      "link": "/zh-cn/docs/user/demos/reference-config-cache.html",
      "meta": {}
    },
    {
      "filename": "registry-only.md",
      "link": "/zh-cn/docs/user/demos/registry-only.html",
      "meta": {}
    },
    {
      "filename": "result-cache.md",
      "link": "/zh-cn/docs/user/demos/result-cache.html",
      "meta": {}
    },
    {
      "filename": "routing-rule-deprecated.md",
      "link": "/zh-cn/docs/user/demos/routing-rule-deprecated.html",
      "meta": {}
    },
    {
      "filename": "routing-rule.md",
      "link": "/zh-cn/docs/user/demos/routing-rule.html",
      "meta": {}
    },
    {
      "filename": "serialization.md",
      "link": "/zh-cn/docs/user/demos/serialization.html",
      "meta": {}
    },
    {
      "filename": "service-container.md",
      "link": "/zh-cn/docs/user/demos/service-container.html",
      "meta": {}
    },
    {
      "filename": "service-downgrade.md",
      "link": "/zh-cn/docs/user/demos/service-downgrade.html",
      "meta": {}
    },
    {
      "filename": "service-group.md",
      "link": "/zh-cn/docs/user/demos/service-group.html",
      "meta": {}
    },
    {
      "filename": "set-host.md",
      "link": "/zh-cn/docs/user/demos/set-host.html",
      "meta": {}
    },
    {
      "filename": "simplify-registry-data.md",
      "link": "/zh-cn/docs/user/demos/simplify-registry-data.html",
      "meta": {}
    },
    {
      "filename": "static-service.md",
      "link": "/zh-cn/docs/user/demos/static-service.html",
      "meta": {}
    },
    {
      "filename": "stickiness.md",
      "link": "/zh-cn/docs/user/demos/stickiness.html",
      "meta": {}
    },
    {
      "filename": "subscribe-only.md",
      "link": "/zh-cn/docs/user/demos/subscribe-only.html",
      "meta": {}
    },
    {
      "filename": "thread-model.md",
      "link": "/zh-cn/docs/user/demos/thread-model.html",
      "meta": {}
    },
    {
      "filename": "token-authorization.md",
      "link": "/zh-cn/docs/user/demos/token-authorization.html",
      "meta": {}
    },
    {
      "filename": "dependencies.md",
      "link": "/zh-cn/docs/user/dependencies.html",
      "meta": {
        "title": "依赖",
        "keywords": "必须依赖, 缺省依赖, 可选依赖",
        "description": "Dubbo 依赖基本介绍"
      }
    },
    {
      "filename": "reference.md",
      "link": "/zh-cn/docs/user/languages/erlang/reference.html",
      "meta": {}
    },
    {
      "filename": "serialization.md",
      "link": "/zh-cn/docs/user/languages/erlang/serialization.html",
      "meta": {}
    },
    {
      "filename": "service.md",
      "link": "/zh-cn/docs/user/languages/erlang/service.html",
      "meta": {}
    },
    {
      "filename": "start.md",
      "link": "/zh-cn/docs/user/languages/erlang/start.html",
      "meta": {}
    },
    {
      "filename": "maturity.md",
      "link": "/zh-cn/docs/user/maturity.html",
      "meta": {
        "title": "成熟度",
        "keywords": "功能成熟度, 策略成熟度",
        "description": "介绍 Dubbo 各个功能、策略的成熟度"
      }
    },
    {
      "filename": "perf-test.md",
      "link": "/zh-cn/docs/user/perf-test.html",
      "meta": {
        "title": "性能测试报告",
        "keywords": "性能测试",
        "description": "Dubbo 2.0 性能测试报告"
      }
    },
    {
      "filename": "architecture.md",
      "link": "/zh-cn/docs/user/preface/architecture.html",
      "meta": {}
    },
    {
      "filename": "background.md",
      "link": "/zh-cn/docs/user/preface/background.html",
      "meta": {}
    },
    {
      "filename": "index.md",
      "link": "/zh-cn/docs/user/preface/index.html",
      "meta": {}
    },
    {
      "filename": "requirements.md",
      "link": "/zh-cn/docs/user/preface/requirements.html",
      "meta": {}
    },
    {
      "filename": "usage.md",
      "link": "/zh-cn/docs/user/preface/usage.html",
      "meta": {}
    },
    {
      "filename": "quick-start.md",
      "link": "/zh-cn/docs/user/quick-start.html",
      "meta": {
        "title": "快速启动",
        "keywords": "XML configuration, Consumer, Provider",
        "description": "使用 XML 配置方式快速上手 Dubbo"
      }
    },
    {
      "filename": "recommend.md",
      "link": "/zh-cn/docs/user/recommend.html",
      "meta": {
        "title": "推荐用法",
        "keywords": "Provider 配置, 管理信息, 缓存, 监控",
        "description": "Dubbo 推荐用法举例"
      }
    },
    {
      "filename": "api.md",
      "link": "/zh-cn/docs/user/references/api.html",
      "meta": {}
    },
    {
      "filename": "maven.md",
      "link": "/zh-cn/docs/user/references/maven.html",
      "meta": {}
    },
    {
      "filename": "introduction.md",
      "link": "/zh-cn/docs/user/references/metadata/introduction.html",
      "meta": {}
    },
    {
      "filename": "metadata-redis.md",
      "link": "/zh-cn/docs/user/references/metadata/metadata-redis.html",
      "meta": {}
    },
    {
      "filename": "metadata-zookeeper.md",
      "link": "/zh-cn/docs/user/references/metadata/metadata-zookeeper.html",
      "meta": {}
    },
    {
      "filename": "dubbo.md",
      "link": "/zh-cn/docs/user/references/protocol/dubbo.html",
      "meta": {}
    },
    {
      "filename": "hessian.md",
      "link": "/zh-cn/docs/user/references/protocol/hessian.html",
      "meta": {}
    },
    {
      "filename": "http.md",
      "link": "/zh-cn/docs/user/references/protocol/http.html",
      "meta": {}
    },
    {
      "filename": "introduction.md",
      "link": "/zh-cn/docs/user/references/protocol/introduction.html",
      "meta": {}
    },
    {
      "filename": "memcached.md",
      "link": "/zh-cn/docs/user/references/protocol/memcached.html",
      "meta": {}
    },
    {
      "filename": "redis.md",
      "link": "/zh-cn/docs/user/references/protocol/redis.html",
      "meta": {}
    },
    {
      "filename": "rest.md",
      "link": "/zh-cn/docs/user/references/protocol/rest.html",
      "meta": {}
    },
    {
      "filename": "rmi.md",
      "link": "/zh-cn/docs/user/references/protocol/rmi.html",
      "meta": {}
    },
    {
      "filename": "thrift.md",
      "link": "/zh-cn/docs/user/references/protocol/thrift.html",
      "meta": {}
    },
    {
      "filename": "webservice.md",
      "link": "/zh-cn/docs/user/references/protocol/webservice.html",
      "meta": {}
    },
    {
      "filename": "qos.md",
      "link": "/zh-cn/docs/user/references/qos.html",
      "meta": {}
    },
    {
      "filename": "introduction.md",
      "link": "/zh-cn/docs/user/references/registry/introduction.html",
      "meta": {}
    },
    {
      "filename": "multicast.md",
      "link": "/zh-cn/docs/user/references/registry/multicast.html",
      "meta": {}
    },
    {
      "filename": "nacos.md",
      "link": "/zh-cn/docs/user/references/registry/nacos.html",
      "meta": {}
    },
    {
      "filename": "redis.md",
      "link": "/zh-cn/docs/user/references/registry/redis.html",
      "meta": {}
    },
    {
      "filename": "simple.md",
      "link": "/zh-cn/docs/user/references/registry/simple.html",
      "meta": {}
    },
    {
      "filename": "zookeeper.md",
      "link": "/zh-cn/docs/user/references/registry/zookeeper.html",
      "meta": {}
    },
    {
      "filename": "telnet.md",
      "link": "/zh-cn/docs/user/references/telnet.html",
      "meta": {}
    },
    {
      "filename": "dubbo-application.md",
      "link": "/zh-cn/docs/user/references/xml/dubbo-application.html",
      "meta": {}
    },
    {
      "filename": "dubbo-argument.md",
      "link": "/zh-cn/docs/user/references/xml/dubbo-argument.html",
      "meta": {}
    },
    {
      "filename": "dubbo-config-center.md",
      "link": "/zh-cn/docs/user/references/xml/dubbo-config-center.html",
      "meta": {}
    },
    {
      "filename": "dubbo-consumer.md",
      "link": "/zh-cn/docs/user/references/xml/dubbo-consumer.html",
      "meta": {}
    },
    {
      "filename": "dubbo-method.md",
      "link": "/zh-cn/docs/user/references/xml/dubbo-method.html",
      "meta": {}
    },
    {
      "filename": "dubbo-module.md",
      "link": "/zh-cn/docs/user/references/xml/dubbo-module.html",
      "meta": {}
    },
    {
      "filename": "dubbo-monitor.md",
      "link": "/zh-cn/docs/user/references/xml/dubbo-monitor.html",
      "meta": {}
    },
    {
      "filename": "dubbo-parameter.md",
      "link": "/zh-cn/docs/user/references/xml/dubbo-parameter.html",
      "meta": {}
    },
    {
      "filename": "dubbo-protocol.md",
      "link": "/zh-cn/docs/user/references/xml/dubbo-protocol.html",
      "meta": {}
    },
    {
      "filename": "dubbo-provider.md",
      "link": "/zh-cn/docs/user/references/xml/dubbo-provider.html",
      "meta": {}
    },
    {
      "filename": "dubbo-reference.md",
      "link": "/zh-cn/docs/user/references/xml/dubbo-reference.html",
      "meta": {}
    },
    {
      "filename": "dubbo-registry.md",
      "link": "/zh-cn/docs/user/references/xml/dubbo-registry.html",
      "meta": {}
    },
    {
      "filename": "dubbo-service.md",
      "link": "/zh-cn/docs/user/references/xml/dubbo-service.html",
      "meta": {}
    },
    {
      "filename": "introduction.md",
      "link": "/zh-cn/docs/user/references/xml/introduction.html",
      "meta": {}
    },
    {
      "filename": "rest.md",
      "link": "/zh-cn/docs/user/rest.html",
      "meta": {
        "title": "在 Dubbo 中开发 REST 风格的远程调用（RESTful Remoting）",
        "keywords": "RESTful Remoting, REST",
        "description": "在 Dubbo 中开发 REST 风格的远程调用"
      }
    },
    {
      "filename": "serialization.md",
      "link": "/zh-cn/docs/user/serialization.html",
      "meta": {}
    },
    {
      "filename": "simple-monitor.md",
      "link": "/zh-cn/docs/user/simple-monitor.html",
      "meta": {}
    },
    {
      "filename": "index.md",
      "link": "/zh-cn/docs/user/versions/index.html",
      "meta": {}
    },
    {
      "filename": "version-270.md",
      "link": "/zh-cn/docs/user/versions/version-270.html",
      "meta": {}
    }
  ]
}